ddeutil/workflow/__about__.py
ddeutil/workflow/__cron.py
ddeutil/workflow/__init__.py
ddeutil/workflow/__main__.py
ddeutil/workflow/__types.py
ddeutil/workflow/audits.py
ddeutil/workflow/conf.py
ddeutil/workflow/errors.py
ddeutil/workflow/event.py
ddeutil/workflow/job.py
ddeutil/workflow/params.py
ddeutil/workflow/result.py
ddeutil/workflow/reusables.py
ddeutil/workflow/stages.py
ddeutil/workflow/traces.py
ddeutil/workflow/utils.py
ddeutil/workflow/workflow.py
ddeutil/workflow/api/__init__.py
ddeutil/workflow/api/log_conf.py
ddeutil/workflow/api/routes/__init__.py
ddeutil/workflow/api/routes/job.py
ddeutil/workflow/api/routes/logs.py
ddeutil/workflow/api/routes/workflows.py
ddeutil/workflow/plugins/__init__.py
ddeutil/workflow/plugins/providers/__init__.py
ddeutil/workflow/plugins/providers/aws.py
ddeutil/workflow/plugins/providers/az.py
ddeutil/workflow/plugins/providers/container.py
ddeutil/workflow/plugins/providers/gcs.py
ddeutil_workflow-0.0.86.dist-info/licenses/LICENSE
ddeutil_workflow-0.0.86.dist-info/METADATA
ddeutil_workflow-0.0.86.dist-info/WHEEL
ddeutil_workflow-0.0.86.dist-info/entry_points.txt
ddeutil_workflow-0.0.86.dist-info/top_level.txt
ddeutil_workflow-0.0.86.dist-info/RECORD
