Metadata-Version: 2.4
Name: ddeutil-workflow
Version: 0.0.86
Summary: Lightweight workflow orchestration with YAML template
Author-email: ddeutils <korawich.anu@gmail.com>
License: MIT
Project-URL: Homepage, https://github.com/ddeutils/ddeutil-workflow/
Project-URL: Source Code, https://github.com/ddeutils/ddeutil-workflow/
Keywords: orchestration,workflow
Classifier: Topic :: Utilities
Classifier: Natural Language :: English
Classifier: Development Status :: 4 - Beta
Classifier: Intended Audience :: Developers
Classifier: Operating System :: OS Independent
Classifier: Programming Language :: Python
Classifier: Programming Language :: Python :: 3 :: Only
Classifier: Programming Language :: Python :: 3.9
Classifier: Programming Language :: Python :: 3.10
Classifier: Programming Language :: Python :: 3.11
Classifier: Programming Language :: Python :: 3.12
Classifier: Programming Language :: Python :: 3.13
Requires-Python: >=3.9.13
License-File: LICENSE
Requires-Dist: ddeutil[checksum]>=0.4.8
Requires-Dist: ddeutil-io[toml,yaml]>=0.2.14
Requires-Dist: pydantic<3.0.0,==2.11.7
Requires-Dist: pydantic-extra-types<3.0.0,>=2.10.4
Requires-Dist: python-dotenv>=1.1.0
Requires-Dist: typer>=0.16.0
Provides-Extra: all
Requires-Dist: fastapi<1.0.0,>=0.115.0; extra == "all"
Requires-Dist: uvicorn; extra == "all"
Requires-Dist: httpx; extra == "all"
Requires-Dist: ujson; extra == "all"
Requires-Dist: aiofiles; extra == "all"
Requires-Dist: aiohttp; extra == "all"
Requires-Dist: requests==2.32.4; extra == "all"
Provides-Extra: docker
Requires-Dist: docker==7.1.0; extra == "docker"
Provides-Extra: azure
Requires-Dist: azure-batch>=13.0.0; extra == "azure"
Requires-Dist: azure-storage-blob>=12.0.0; extra == "azure"
Provides-Extra: aws
Requires-Dist: boto3>=1.39.0; extra == "aws"
Provides-Extra: gcp
Requires-Dist: google-cloud-batch>=0.17.0; extra == "gcp"
Requires-Dist: google-cloud-storage>=2.10.0; extra == "gcp"
Dynamic: license-file
